LICENSE.txt
README.md
beancount_bd/__init__.py
beancount_bd-1.0.0.dist-info/LICENSE.txt
beancount_bd-1.0.0.dist-info/WHEEL
beancount_bd-1.0.0.dist-info/METADATA
beancount_bd-1.0.0.dist-info/RECORD
