Metadata-Version: 2.1
Name: beancount-bd
Version: 1.0.0
Summary: Beancount order history importer for Bourse Direct brooker
Home-page: https://github.com/ArthurFDLR/beancount-bd
License: MIT
Keywords: banking,beancount,cli-accounting,finance
Author: Arthur Findelair
Author-email: arthfind@gmail.com
Requires-Python: >=3.8,<4.0
Classifier: Development Status :: 5 - Production/Stable
Classifier: Environment :: Plugins
Classifier: Intended Audience :: End Users/Desktop
Classifier: Intended Audience :: Financial and Insurance Industry
Classifier: License :: OSI Approved :: MIT License
Classifier: Programming Language :: Python :: 3
Classifier: Programming Language :: Python :: 3 :: Only
Classifier: Programming Language :: Python :: 3.10
Classifier: Programming Language :: Python :: 3.6
Classifier: Programming Language :: Python :: 3.7
Classifier: Programming Language :: Python :: 3.8
Classifier: Programming Language :: Python :: 3.9
Requires-Dist: beancount (>=2.2,<3.0)
Requires-Dist: pandas (>=1.4.3,<2.0.0)
Project-URL: Repository, https://github.com/ArthurFDLR/beancount-bd
